<?xml version='1.0' encoding='UTF-8'?>
<COSMED_OMNIA_EXPORT>
  <Information>
    <Export Version="2.3" Type="ErgoProtocol" S_Data="281474976776197">cLWiPw==$NKDvFZox/85BnzcEwLxxMA==$sXnx0yFFXsKUUGSnFGU6rA==</Export>
  </Information>
  <ErgoProtocol>
    <RecordID>eb68ea14-7411-4990-a956-d96fb657b1df</RecordID>
    <LastEdit>635621472000000000</LastEdit>
    <Protected>False</Protected>
    <Name>PRBSV2 STEP P06</Name>
    <ProtocolType>0</ProtocolType>
    <ErgometerType>1</ErgometerType>
    <RMR>False</RMR>
    <EOT>False</EOT>
    <ErgoProtocolStep>
      <RecordID>e9c87acd-cf19-43f9-b1d8-d2a2da55580a</RecordID>
      <LastEdit>635621472000000000</LastEdit>
      <protocolID>eb68ea14-7411-4990-a956-d96fb657b1df</protocolID>
      <Time>0</Time>
      <Load1>0</Load1>
      <Load2>0</Load2>
      <Load3>0</Load3>
      <Phase>1</Phase>
      <BP>False</BP>
      <FV>False</FV>
      <ECG>False</ECG>
      <ABG>False</ABG>
      <SPO2>False</SPO2>
    </ErgoProtocolStep>
    <ErgoProtocolStep>
      <RecordID>0ff0a6e6-f1bc-4d37-bf0d-29418085fa77</RecordID>
      <LastEdit>635621472000000000</LastEdit>
      <protocolID>eb68ea14-7411-4990-a956-d96fb657b1df</protocolID>
      <Time>120</Time>
      <Load1>67</Load1>
      <Load2>0</Load2>
      <Load3>0</Load3>
      <Phase>2</Phase>
      <BP>False</BP>
      <FV>False</FV>
      <ECG>False</ECG>
      <ABG>False</ABG>
      <SPO2>False</SPO2>
    </ErgoProtocolStep>
    <ErgoProtocolStep>
      <RecordID>11edbb8a-77ee-4c17-b382-ef247cea5d82</RecordID>
      <LastEdit>635621472000000000</LastEdit>
      <protocolID>eb68ea14-7411-4990-a956-d96fb657b1df</protocolID>
      <Time>330</Time>
      <Load1>25</Load1>
      <Load2>0</Load2>
      <Load3>0</Load3>
      <Phase>2</Phase>
      <BP>False</BP>
      <FV>False</FV>
      <ECG>False</ECG>
      <ABG>False</ABG>
      <SPO2>False</SPO2>
    </ErgoProtocolStep>
    <ErgoProtocolStep>
      <RecordID>ddc1eea6-4939-4f50-8e6e-f068d0b45f57</RecordID>
      <LastEdit>635621472000000000</LastEdit>
      <protocolID>eb68ea14-7411-4990-a956-d96fb657b1df</protocolID>
      <Time>360</Time>
      <Load1>102</Load1>
      <Load2>0</Load2>
      <Load3>0</Load3>
      <Phase>3</Phase>
      <BP>False</BP>
      <FV>False</FV>
      <ECG>False</ECG>
      <ABG>False</ABG>
      <SPO2>False</SPO2>
    </ErgoProtocolStep>
    <ErgoProtocolStep>
      <RecordID>31ea6094-93ea-42c0-8b9a-9d648c50eaa5</RecordID>
      <LastEdit>635621472000000000</LastEdit>
      <protocolID>eb68ea14-7411-4990-a956-d96fb657b1df</protocolID>
      <Time>720</Time>
      <Load1>25</Load1>
      <Load2>0</Load2>
      <Load3>0</Load3>
      <Phase>3</Phase>
      <BP>False</BP>
      <FV>False</FV>
      <ECG>False</ECG>
      <ABG>False</ABG>
      <SPO2>False</SPO2>
    </ErgoProtocolStep>
    <ErgoProtocolStep>
      <RecordID>aa5ccf26-90fa-4d5e-822b-db7d99f6b42c</RecordID>
      <LastEdit>635621472000000000</LastEdit>
      <protocolID>eb68ea14-7411-4990-a956-d96fb657b1df</protocolID>
      <Time>1080</Time>
      <Load1>102</Load1>
      <Load2>0</Load2>
      <Load3>0</Load3>
      <Phase>2</Phase>
      <BP>False</BP>
      <FV>False</FV>
      <ECG>False</ECG>
      <ABG>False</ABG>
      <SPO2>False</SPO2>
    </ErgoProtocolStep>
    <ErgoProtocolStep>
      <RecordID>2ed3aa99-81ad-4048-acf2-c908acb4223b</RecordID>
      <LastEdit>635621472000000000</LastEdit>
      <protocolID>eb68ea14-7411-4990-a956-d96fb657b1df</protocolID>
      <Time>1140</Time>
      <Load1>25</Load1>
      <Load2>0</Load2>
      <Load3>0</Load3>
      <Phase>2</Phase>
      <BP>False</BP>
      <FV>False</FV>
      <ECG>False</ECG>
      <ABG>False</ABG>
      <SPO2>False</SPO2>
    </ErgoProtocolStep>
    <ErgoProtocolStep>
      <RecordID>78b987a3-e501-443d-804e-189719b4ec94</RecordID>
      <LastEdit>635621472000000000</LastEdit>
      <protocolID>eb68ea14-7411-4990-a956-d96fb657b1df</protocolID>
      <Time>1170</Time>
      <Load1>102</Load1>
      <Load2>0</Load2>
      <Load3>0</Load3>
      <Phase>2</Phase>
      <BP>False</BP>
      <FV>False</FV>
      <ECG>False</ECG>
      <ABG>False</ABG>
      <SPO2>False</SPO2>
    </ErgoProtocolStep>
    <ErgoProtocolStep>
      <RecordID>b9802e61-2696-44c3-a195-c29fb341ef32</RecordID>
      <LastEdit>635621472000000000</LastEdit>
      <protocolID>eb68ea14-7411-4990-a956-d96fb657b1df</protocolID>
      <Time>1200</Time>
      <Load1>25</Load1>
      <Load2>0</Load2>
      <Load3>0</Load3>
      <Phase>2</Phase>
      <BP>False</BP>
      <FV>False</FV>
      <ECG>False</ECG>
      <ABG>False</ABG>
      <SPO2>False</SPO2>
    </ErgoProtocolStep>
    <ErgoProtocolStep>
      <RecordID>c454a2f2-a610-4aea-b342-79df39dddf2c</RecordID>
      <LastEdit>635621472000000000</LastEdit>
      <protocolID>eb68ea14-7411-4990-a956-d96fb657b1df</protocolID>
      <Time>1260</Time>
      <Load1>102</Load1>
      <Load2>0</Load2>
      <Load3>0</Load3>
      <Phase>2</Phase>
      <BP>False</BP>
      <FV>False</FV>
      <ECG>False</ECG>
      <ABG>False</ABG>
      <SPO2>False</SPO2>
    </ErgoProtocolStep>
    <ErgoProtocolStep>
      <RecordID>f46fcd4b-ca2a-47f1-8697-1e7cb3a23389</RecordID>
      <LastEdit>635621472000000000</LastEdit>
      <protocolID>eb68ea14-7411-4990-a956-d96fb657b1df</protocolID>
      <Time>1290</Time>
      <Load1>25</Load1>
      <Load2>0</Load2>
      <Load3>0</Load3>
      <Phase>3</Phase>
      <BP>False</BP>
      <FV>False</FV>
      <ECG>False</ECG>
      <ABG>False</ABG>
      <SPO2>False</SPO2>
    </ErgoProtocolStep>
    <ErgoProtocolStep>
      <RecordID>83b38d63-9fc6-4968-ae77-311aab92290f</RecordID>
      <LastEdit>635621472000000000</LastEdit>
      <protocolID>eb68ea14-7411-4990-a956-d96fb657b1df</protocolID>
      <Time>1410</Time>
      <Load1>102</Load1>
      <Load2>0</Load2>
      <Load3>0</Load3>
      <Phase>3</Phase>
      <BP>False</BP>
      <FV>False</FV>
      <ECG>False</ECG>
      <ABG>False</ABG>
      <SPO2>False</SPO2>
    </ErgoProtocolStep>
    <ErgoProtocolStep>
      <RecordID>1959f260-1dab-44f4-ac95-8b68bd3598ba</RecordID>
      <LastEdit>635621472000000000</LastEdit>
      <protocolID>eb68ea14-7411-4990-a956-d96fb657b1df</protocolID>
      <Time>1440</Time>
      <Load1>25</Load1>
      <Load2>0</Load2>
      <Load3>0</Load3>
      <Phase>3</Phase>
      <BP>False</BP>
      <FV>False</FV>
      <ECG>False</ECG>
      <ABG>False</ABG>
      <SPO2>False</SPO2>
    </ErgoProtocolStep>
    <ErgoProtocolStep>
      <RecordID>343c76f1-704e-4ae9-8607-fcf697daa2a1</RecordID>
      <LastEdit>635621472000000000</LastEdit>
      <protocolID>eb68ea14-7411-4990-a956-d96fb657b1df</protocolID>
      <Time>1470</Time>
      <Load1>102</Load1>
      <Load2>0</Load2>
      <Load3>0</Load3>
      <Phase>3</Phase>
      <BP>False</BP>
      <FV>False</FV>
      <ECG>False</ECG>
      <ABG>False</ABG>
      <SPO2>False</SPO2>
    </ErgoProtocolStep>
    <ErgoProtocolStep>
      <RecordID>780dc26c-d8e5-4ef8-8b1e-65df252754f3</RecordID>
      <LastEdit>635621472000000000</LastEdit>
      <protocolID>eb68ea14-7411-4990-a956-d96fb657b1df</protocolID>
      <Time>1500</Time>
      <Load1>25</Load1>
      <Load2>0</Load2>
      <Load3>0</Load3>
      <Phase>3</Phase>
      <BP>False</BP>
      <FV>False</FV>
      <ECG>False</ECG>
      <ABG>False</ABG>
      <SPO2>False</SPO2>
    </ErgoProtocolStep>
    <ErgoProtocolStep>
      <RecordID>da7f758e-a23e-48d5-bb9f-ba82ee5debbb</RecordID>
      <LastEdit>635621472000000000</LastEdit>
      <protocolID>eb68ea14-7411-4990-a956-d96fb657b1df</protocolID>
      <Time>1530</Time>
      <Load1>102</Load1>
      <Load2>0</Load2>
      <Load3>0</Load3>
      <Phase>3</Phase>
      <BP>False</BP>
      <FV>False</FV>
      <ECG>False</ECG>
      <ABG>False</ABG>
      <SPO2>False</SPO2>
    </ErgoProtocolStep>
    <ErgoProtocolStep>
      <RecordID>a2dcd83d-de63-4e81-91b9-52af5954ac37</RecordID>
      <LastEdit>635621472000000000</LastEdit>
      <protocolID>eb68ea14-7411-4990-a956-d96fb657b1df</protocolID>
      <Time>1620</Time>
      <Load1>25</Load1>
      <Load2>0</Load2>
      <Load3>0</Load3>
      <Phase>3</Phase>
      <BP>False</BP>
      <FV>False</FV>
      <ECG>False</ECG>
      <ABG>False</ABG>
      <SPO2>False</SPO2>
    </ErgoProtocolStep>
    <ErgoProtocolStep>
      <RecordID>a2d959f3-bd6f-4812-be4a-0db7abe60104</RecordID>
      <LastEdit>635621472000000000</LastEdit>
      <protocolID>eb68ea14-7411-4990-a956-d96fb657b1df</protocolID>
      <Time>1650</Time>
      <Load1>102</Load1>
      <Load2>0</Load2>
      <Load3>0</Load3>
      <Phase>3</Phase>
      <BP>False</BP>
      <FV>False</FV>
      <ECG>False</ECG>
      <ABG>False</ABG>
      <SPO2>False</SPO2>
    </ErgoProtocolStep>
    <ErgoProtocolStep>
      <RecordID>7de3dea8-3782-4d31-8c6d-128c1453fd82</RecordID>
      <LastEdit>635621472000000000</LastEdit>
      <protocolID>eb68ea14-7411-4990-a956-d96fb657b1df</protocolID>
      <Time>1710</Time>
      <Load1>25</Load1>
      <Load2>0</Load2>
      <Load3>0</Load3>
      <Phase>3</Phase>
      <BP>False</BP>
      <FV>False</FV>
      <ECG>False</ECG>
      <ABG>False</ABG>
      <SPO2>False</SPO2>
    </ErgoProtocolStep>
    <ErgoProtocolStep>
      <RecordID>a15454fb-2501-4ef9-8f87-9f3d3c6882fa</RecordID>
      <LastEdit>635621472000000000</LastEdit>
      <protocolID>eb68ea14-7411-4990-a956-d96fb657b1df</protocolID>
      <Time>1800</Time>
      <Load1>102</Load1>
      <Load2>0</Load2>
      <Load3>0</Load3>
      <Phase>3</Phase>
      <BP>False</BP>
      <FV>False</FV>
      <ECG>False</ECG>
      <ABG>False</ABG>
      <SPO2>False</SPO2>
    </ErgoProtocolStep>
    <ErgoProtocolStep>
      <RecordID>4e325019-fbe2-4d63-884d-715d0750420b</RecordID>
      <LastEdit>635621472000000000</LastEdit>
      <protocolID>eb68ea14-7411-4990-a956-d96fb657b1df</protocolID>
      <Time>1950</Time>
      <Load1>25</Load1>
      <Load2>0</Load2>
      <Load3>0</Load3>
      <Phase>3</Phase>
      <BP>False</BP>
      <FV>False</FV>
      <ECG>False</ECG>
      <ABG>False</ABG>
      <SPO2>False</SPO2>
    </ErgoProtocolStep>
    <ErgoProtocolStep>
      <RecordID>77f3afb8-6995-476f-93c8-6ffcccac77a1</RecordID>
      <LastEdit>635621472000000000</LastEdit>
      <protocolID>eb68ea14-7411-4990-a956-d96fb657b1df</protocolID>
      <Time>2010</Time>
      <Load1>102</Load1>
      <Load2>0</Load2>
      <Load3>0</Load3>
      <Phase>3</Phase>
      <BP>False</BP>
      <FV>False</FV>
      <ECG>False</ECG>
      <ABG>False</ABG>
      <SPO2>False</SPO2>
    </ErgoProtocolStep>
    <ErgoProtocolStep>
      <RecordID>7ae67d6a-138a-4302-94f9-765d4396998b</RecordID>
      <LastEdit>635621472000000000</LastEdit>
      <protocolID>eb68ea14-7411-4990-a956-d96fb657b1df</protocolID>
      <Time>2070</Time>
      <Load1>25</Load1>
      <Load2>0</Load2>
      <Load3>0</Load3>
      <Phase>3</Phase>
      <BP>False</BP>
      <FV>False</FV>
      <ECG>False</ECG>
      <ABG>False</ABG>
      <SPO2>False</SPO2>
    </ErgoProtocolStep>
    <ErgoProtocolStep>
      <RecordID>95b123c4-94df-41c9-a3f4-b08614aed1b2</RecordID>
      <LastEdit>635621472000000000</LastEdit>
      <protocolID>eb68ea14-7411-4990-a956-d96fb657b1df</protocolID>
      <Time>2100</Time>
      <Load1>102</Load1>
      <Load2>0</Load2>
      <Load3>0</Load3>
      <Phase>3</Phase>
      <BP>False</BP>
      <FV>False</FV>
      <ECG>False</ECG>
      <ABG>False</ABG>
      <SPO2>False</SPO2>
    </ErgoProtocolStep>
    <ErgoProtocolStep>
      <RecordID>a7982705-d18e-4c21-af37-c1f4d2338847</RecordID>
      <LastEdit>635621472000000000</LastEdit>
      <protocolID>eb68ea14-7411-4990-a956-d96fb657b1df</protocolID>
      <Time>2130</Time>
      <Load1>25</Load1>
      <Load2>0</Load2>
      <Load3>0</Load3>
      <Phase>3</Phase>
      <BP>False</BP>
      <FV>False</FV>
      <ECG>False</ECG>
      <ABG>False</ABG>
      <SPO2>False</SPO2>
    </ErgoProtocolStep>
    <ErgoProtocolStep>
      <RecordID>578e174a-2ba9-445f-8d05-64084ca313a0</RecordID>
      <LastEdit>635621472000000000</LastEdit>
      <protocolID>eb68ea14-7411-4990-a956-d96fb657b1df</protocolID>
      <Time>2190</Time>
      <Load1>102</Load1>
      <Load2>0</Load2>
      <Load3>0</Load3>
      <Phase>3</Phase>
      <BP>False</BP>
      <FV>False</FV>
      <ECG>False</ECG>
      <ABG>False</ABG>
      <SPO2>False</SPO2>
    </ErgoProtocolStep>
    <ErgoProtocolStep>
      <RecordID>85c09dd4-b40a-4ea6-ba7b-ffedaa299614</RecordID>
      <LastEdit>635621472000000000</LastEdit>
      <protocolID>eb68ea14-7411-4990-a956-d96fb657b1df</protocolID>
      <Time>2220</Time>
      <Load1>25</Load1>
      <Load2>0</Load2>
      <Load3>0</Load3>
      <Phase>3</Phase>
      <BP>False</BP>
      <FV>False</FV>
      <ECG>False</ECG>
      <ABG>False</ABG>
      <SPO2>False</SPO2>
    </ErgoProtocolStep>
    <ErgoProtocolStep>
      <RecordID>4f2cc500-4ddf-4219-ac93-b8cd0c668702</RecordID>
      <LastEdit>635621472000000000</LastEdit>
      <protocolID>eb68ea14-7411-4990-a956-d96fb657b1df</protocolID>
      <Time>2340</Time>
      <Load1>102</Load1>
      <Load2>0</Load2>
      <Load3>0</Load3>
      <Phase>3</Phase>
      <BP>False</BP>
      <FV>False</FV>
      <ECG>False</ECG>
      <ABG>False</ABG>
      <SPO2>False</SPO2>
    </ErgoProtocolStep>
    <ErgoProtocolStep>
      <RecordID>c66241e1-6a2e-464c-a977-1acecb9cfd84</RecordID>
      <LastEdit>635621472000000000</LastEdit>
      <protocolID>eb68ea14-7411-4990-a956-d96fb657b1df</protocolID>
      <Time>2370</Time>
      <Load1>25</Load1>
      <Load2>0</Load2>
      <Load3>0</Load3>
      <Phase>3</Phase>
      <BP>False</BP>
      <FV>False</FV>
      <ECG>False</ECG>
      <ABG>False</ABG>
      <SPO2>False</SPO2>
    </ErgoProtocolStep>
    <ErgoProtocolStep>
      <RecordID>b44ea82b-a0a5-47b1-95f0-13d93b2be4fc</RecordID>
      <LastEdit>635621472000000000</LastEdit>
      <protocolID>eb68ea14-7411-4990-a956-d96fb657b1df</protocolID>
      <Time>2400</Time>
      <Load1>102</Load1>
      <Load2>0</Load2>
      <Load3>0</Load3>
      <Phase>3</Phase>
      <BP>False</BP>
      <FV>False</FV>
      <ECG>False</ECG>
      <ABG>False</ABG>
      <SPO2>False</SPO2>
    </ErgoProtocolStep>
    <ErgoProtocolStep>
      <RecordID>1bc8bf93-9c42-4eaa-8f72-d284edbf2461</RecordID>
      <LastEdit>635621472000000000</LastEdit>
      <protocolID>eb68ea14-7411-4990-a956-d96fb657b1df</protocolID>
      <Time>2430</Time>
      <Load1>25</Load1>
      <Load2>0</Load2>
      <Load3>0</Load3>
      <Phase>3</Phase>
      <BP>False</BP>
      <FV>False</FV>
      <ECG>False</ECG>
      <ABG>False</ABG>
      <SPO2>False</SPO2>
    </ErgoProtocolStep>
    <ErgoProtocolStep>
      <RecordID>ee4f9e40-bb07-4012-90fb-56074e52e7b2</RecordID>
      <LastEdit>635621472000000000</LastEdit>
      <protocolID>eb68ea14-7411-4990-a956-d96fb657b1df</protocolID>
      <Time>2460</Time>
      <Load1>102</Load1>
      <Load2>0</Load2>
      <Load3>0</Load3>
      <Phase>3</Phase>
      <BP>False</BP>
      <FV>False</FV>
      <ECG>False</ECG>
      <ABG>False</ABG>
      <SPO2>False</SPO2>
    </ErgoProtocolStep>
    <ErgoProtocolStep>
      <RecordID>0e9bde6d-5d63-4a3c-89cb-866ded1960ea</RecordID>
      <LastEdit>635621472000000000</LastEdit>
      <protocolID>eb68ea14-7411-4990-a956-d96fb657b1df</protocolID>
      <Time>2550</Time>
      <Load1>25</Load1>
      <Load2>0</Load2>
      <Load3>0</Load3>
      <Phase>3</Phase>
      <BP>False</BP>
      <FV>False</FV>
      <ECG>False</ECG>
      <ABG>False</ABG>
      <SPO2>False</SPO2>
    </ErgoProtocolStep>
    <ErgoProtocolStep>
      <RecordID>ffc49f00-9c5e-4082-832e-e3ddfd99e8ee</RecordID>
      <LastEdit>635621472000000000</LastEdit>
      <protocolID>eb68ea14-7411-4990-a956-d96fb657b1df</protocolID>
      <Time>2580</Time>
      <Load1>102</Load1>
      <Load2>0</Load2>
      <Load3>0</Load3>
      <Phase>3</Phase>
      <BP>False</BP>
      <FV>False</FV>
      <ECG>False</ECG>
      <ABG>False</ABG>
      <SPO2>False</SPO2>
    </ErgoProtocolStep>
    <ErgoProtocolStep>
      <RecordID>a51497bf-8248-4ff6-b7b6-231dc6ad654b</RecordID>
      <LastEdit>635621472000000000</LastEdit>
      <protocolID>eb68ea14-7411-4990-a956-d96fb657b1df</protocolID>
      <Time>2640</Time>
      <Load1>25</Load1>
      <Load2>0</Load2>
      <Load3>0</Load3>
      <Phase>3</Phase>
      <BP>False</BP>
      <FV>False</FV>
      <ECG>False</ECG>
      <ABG>False</ABG>
      <SPO2>False</SPO2>
    </ErgoProtocolStep>
    <ErgoProtocolStep>
      <RecordID>00058de6-ffce-4a5d-848f-8e200d946669</RecordID>
      <LastEdit>635621472000000000</LastEdit>
      <protocolID>eb68ea14-7411-4990-a956-d96fb657b1df</protocolID>
      <Time>2730</Time>
      <Load1>102</Load1>
      <Load2>0</Load2>
      <Load3>0</Load3>
      <Phase>3</Phase>
      <BP>False</BP>
      <FV>False</FV>
      <ECG>False</ECG>
      <ABG>False</ABG>
      <SPO2>False</SPO2>
    </ErgoProtocolStep>
    <ErgoProtocolStep>
      <RecordID>87e883eb-9348-4cae-87ef-d921c3254112</RecordID>
      <LastEdit>635621472000000000</LastEdit>
      <protocolID>eb68ea14-7411-4990-a956-d96fb657b1df</protocolID>
      <Time>2880</Time>
      <Load1>25</Load1>
      <Load2>0</Load2>
      <Load3>0</Load3>
      <Phase>3</Phase>
      <BP>False</BP>
      <FV>False</FV>
      <ECG>False</ECG>
      <ABG>False</ABG>
      <SPO2>False</SPO2>
    </ErgoProtocolStep>
    <ErgoProtocolStep>
      <RecordID>4978a17a-0881-4bca-96ec-fcdbafd9043a</RecordID>
      <LastEdit>635621472000000000</LastEdit>
      <protocolID>eb68ea14-7411-4990-a956-d96fb657b1df</protocolID>
      <Time>2940</Time>
      <Load1>102</Load1>
      <Load2>0</Load2>
      <Load3>0</Load3>
      <Phase>3</Phase>
      <BP>False</BP>
      <FV>False</FV>
      <ECG>False</ECG>
      <ABG>False</ABG>
      <SPO2>False</SPO2>
    </ErgoProtocolStep>
    <ErgoProtocolStep>
      <RecordID>9fe8f059-4029-4abb-abe7-cbf546599b0e</RecordID>
      <LastEdit>635621472000000000</LastEdit>
      <protocolID>eb68ea14-7411-4990-a956-d96fb657b1df</protocolID>
      <Time>3000</Time>
      <Load1>25</Load1>
      <Load2>0</Load2>
      <Load3>0</Load3>
      <Phase>3</Phase>
      <BP>False</BP>
      <FV>False</FV>
      <ECG>False</ECG>
      <ABG>False</ABG>
      <SPO2>False</SPO2>
    </ErgoProtocolStep>
    <ErgoProtocolStep>
      <RecordID>ada854c4-d9dc-41c0-bb6b-eb0e0682b806</RecordID>
      <LastEdit>635621472000000000</LastEdit>
      <protocolID>eb68ea14-7411-4990-a956-d96fb657b1df</protocolID>
      <Time>3030</Time>
      <Load1>102</Load1>
      <Load2>0</Load2>
      <Load3>0</Load3>
      <Phase>3</Phase>
      <BP>False</BP>
      <FV>False</FV>
      <ECG>False</ECG>
      <ABG>False</ABG>
      <SPO2>False</SPO2>
    </ErgoProtocolStep>
    <ErgoProtocolStep>
      <RecordID>9b7db676-ce0b-4c3a-84bd-86ec2db550bf</RecordID>
      <LastEdit>635621472000000000</LastEdit>
      <protocolID>eb68ea14-7411-4990-a956-d96fb657b1df</protocolID>
      <Time>3060</Time>
      <Load1>25</Load1>
      <Load2>0</Load2>
      <Load3>0</Load3>
      <Phase>3</Phase>
      <BP>False</BP>
      <FV>False</FV>
      <ECG>False</ECG>
      <ABG>False</ABG>
      <SPO2>False</SPO2>
    </ErgoProtocolStep>
    <ErgoProtocolStep>
      <RecordID>c3bf42d9-04d4-41e3-a29f-dc68dbc5e5ba</RecordID>
      <LastEdit>635621472000000000</LastEdit>
      <protocolID>eb68ea14-7411-4990-a956-d96fb657b1df</protocolID>
      <Time>3120</Time>
      <Load1>102</Load1>
      <Load2>0</Load2>
      <Load3>0</Load3>
      <Phase>3</Phase>
      <BP>False</BP>
      <FV>False</FV>
      <ECG>False</ECG>
      <ABG>False</ABG>
      <SPO2>False</SPO2>
    </ErgoProtocolStep>
    <ErgoProtocolStep>
      <RecordID>39863e3a-91e9-48e4-8d72-5944165e92e9</RecordID>
      <LastEdit>635621472000000000</LastEdit>
      <protocolID>eb68ea14-7411-4990-a956-d96fb657b1df</protocolID>
      <Time>3150</Time>
      <Load1>102</Load1>
      <Load2>0</Load2>
      <Load3>0</Load3>
      <Phase>3</Phase>
      <BP>False</BP>
      <FV>False</FV>
      <ECG>False</ECG>
      <ABG>False</ABG>
      <SPO2>False</SPO2>
    </ErgoProtocolStep>
  </ErgoProtocol>
</COSMED_OMNIA_EXPORT>
